
{
  "ID": 95,
  "Name": "Eucalyptus Forest",
  "Class": "biomesoplenty.common.biome.overworld.BiomeGenEucalyptusForest",
  "Color": 8704360,
  "Root Height": 0.0,
  "Height Variation": 0.2,
  "Top Block": "minecraft:grass",
  "Filler Block": "minecraft:dirt",
  "Grass Color": "Not set. Check in-game.",
  "Foliage Color": "Not set. Check in-game.",
  "Water Color": "16777215",
  "Temperature": 0.9,
  "Humidity": 1.0,
  "Water Tint": 16777215,
  "Enable Rain": true,
  "Enable Snow": false,
  "Dictionary Types": [
    "HOT",
    "WET",
    "PLAINS"
  ],
  "BiomeManager Entries": {},
  "Spawnable Creatures": [],
  "Spawnable Monsters": [],
  "Spawnable Water Creatures": [],
  "Spawnable Cave Creatures": [],
  "Spawn Biome": true,
  "Tweaked": false
}