
{
  "ID": 74,
  "Name": "Marsh",
  "Class": "biomesoplenty.common.biome.overworld.BiomeGenMarsh",
  "Color": 6725742,
  "Root Height": 0.1,
  "Height Variation": 0.05,
  "Top Block": "minecraft:grass",
  "Filler Block": "minecraft:dirt",
  "Grass Color": "Not set. Check in-game.",
  "Foliage Color": "Not set. Check in-game.",
  "Water Color": "16777215",
  "Temperature": 0.5,
  "Humidity": 0.9,
  "Water Tint": 16777215,
  "Enable Rain": true,
  "Enable Snow": false,
  "Dictionary Types": [
    "SPARSE",
    "WET",
    "LUSH",
    "OCEAN",
    "RIVER",
    "SWAMP"
  ],
  "BiomeManager Entries": {},
  "Spawnable Creatures": [],
  "Spawnable Monsters": [],
  "Spawnable Water Creatures": [],
  "Spawnable Cave Creatures": [],
  "Spawn Biome": true,
  "Tweaked": false
}